{
    "LevelName": "",
    "horizontal": 97.0,
    "name": "Level",
    "objects": [
        {
            "object": {
                "IndividualSettings": null,
                "pos": [
                    1000.0,
                    130.0
                ],
                "scale": [
                    64.0,
                    64.0
                ],
                "tag": 5
            }
        },
        {
            "object": {
                "IndividualSettings": null,
                "pos": [
                    150.0,
                    600.0
                ],
                "scale": [
                    64.0,
                    64.0
                ],
                "tag": 0
            }
        },
        {
            "object": {
                "IndividualSettings": null,
                "pos": [
                    500.0,
                    252.0
                ],
                "scale": [
                    64.0,
                    64.0
                ],
                "tag": 3
            }
        },
        {
            "object": {
                "IndividualSettings": null,
                "pos": [
                    500.0,
                    186.0
                ],
                "scale": [
                    64.0,
                    64.0
                ],
                "tag": 3
            }
        },
        {
            "object": {
                "IndividualSettings": null,
                "pos": [
                    566.0,
                    252.0
                ],
                "scale": [
                    64.0,
                    64.0
                ],
                "tag": 3
            }
        },
        {
            "object": {
                "IndividualSettings": null,
                "pos": [
                    697.0,
                    186.0
                ],
                "scale": [
                    64.0,
                    64.0
                ],
                "tag": 3
            }
        },
        {
            "object": {
                "IndividualSettings": null,
                "pos": [
                    697.0,
                    252.0
                ],
                "scale": [
                    64.0,
                    64.0
                ],
                "tag": 3
            }
        },
        {
            "object": {
                "IndividualSettings": null,
                "pos": [
                    500.0,
                    120.0
                ],
                "scale": [
                    64.0,
                    64.0
                ],
                "tag": 3
            }
        },
        {
            "object": {
                "IndividualSettings": null,
                "pos": [
                    697.0,
                    120.0
                ],
                "scale": [
                    64.0,
                    64.0
                ],
                "tag": 3
            }
        },
        {
            "object": {
                "IndividualSettings": null,
                "pos": [
                    599.0,
                    165.0
                ],
                "scale": [
                    64.0,
                    64.0
                ],
                "tag": 6
            }
        },
        {
            "object": {
                "IndividualSettings": null,
                "pos": [
                    631.0,
                    252.0
                ],
                "scale": [
                    64.0,
                    64.0
                ],
                "tag": 3
            }
        }
    ]
}